[
  {
    "id": 9223372036854776000,
    "photoUrls": [],
    "tags": [],
    "status": "sold"
  },
  {
    "id": 3134226,
    "category": {
      "id": 43656969,
      "name": "nostrud"
    },
    "name": "doggie",
    "photoUrls": [
      "id ad Excepteur",
      "adipisicing anim irure enim Lorem"
    ],
    "tags": [
      {
        "id": 66437993,
        "name": "reprehenderit Duis sunt"
      },
      {
        "id": 46232334,
        "name": "commodo sunt ex"
      }
    ],
    "status": "sold"
  },
  {
    "id": 922337203685477,
    "category": {
      "id": 0,
      "name": "string"
    },
    "name": "doggie",
    "photoUrls": [
      "string"
    ],
    "tags": [
      {
        "id": 0,
        "name": "string"
      }
    ],
    "status": "sold"
  },
  {
    "id": 2269,
    "category": {
      "id": 640,
      "name": "Faker.Extensions.EnumerableExtensions+<Times>d__0`1[System.String]"
    },
    "name": "Faker.Extensions.EnumerableExtensions+<Times>d__0`1[System.String]",
    "photoUrls": [
      "",
      ""
    ],
    "tags": [
      {
        "id": 313,
        "name": "Faker.Extensions.EnumerableExtensions+<Times>d__0`1[System.String]"
      }
    ],
    "status": "sold"
  },
  {
    "id": 2965,
    "category": {
      "id": 1612,
      "name": "Faker.Extensions.EnumerableExtensions+<Times>d__0`1[System.String]"
    },
    "name": "Unicorn",
    "photoUrls": [
      "",
      ""
    ],
    "tags": [
      {
        "id": 368,
        "name": "Faker.Extensions.EnumerableExtensions+<Times>d__0`1[System.String]"
      }
    ],
    "status": "sold"
  },
  {
    "id": 233,
    "category": {
      "id": 0,
      "name": "test test dog"
    },
    "name": "Tobbi i Bobbi",
    "photoUrls": [
      "string"
    ],
    "tags": [
      {
        "id": 0,
        "name": "Tobbi i Bobbi"
      }
    ],
    "status": "sold"
  },
  {
    "id": 1680011439979,
    "name": "Lucy",
    "photoUrls": [],
    "tags": [],
    "status": "sold"
  },
  {
    "id": 37930519,
    "category": {
      "id": -20083820,
      "name": "est"
    },
    "name": "doggie",
    "photoUrls": [
      "consectetur",
      "proident sint"
    ],
    "tags": [
      {
        "id": -50305895,
        "name": "occaecat labore"
      },
      {
        "id": -90748378,
        "name": "Duis irure"
      }
    ],
    "status": "sold"
  },
  {
    "id": 3699,
    "category": {
      "id": 1366825701,
      "name": "automation"
    },
    "name": "hello kity",
    "photoUrls": [
      "foo.bar.com/1",
      "foo.bar.com/2"
    ],
    "tags": [
      {
        "id": 332,
        "name": "tagss"
      }
    ],
    "status": "sold"
  },
  {
    "id": 9084,
    "category": {
      "id": 1366825701,
      "name": "automation"
    },
    "name": "hello kity",
    "photoUrls": [
      "foo.bar.com/1",
      "foo.bar.com/2"
    ],
    "tags": [
      {
        "id": 332,
        "name": "tagss"
      }
    ],
    "status": "sold"
  },
  {
    "id": 4779,
    "category": {
      "id": 1366825701,
      "name": "automation"
    },
    "name": "hello kity",
    "photoUrls": [
      "foo.bar.com/1",
      "foo.bar.com/2"
    ],
    "tags": [
      {
        "id": 332,
        "name": "tagss"
      }
    ],
    "status": "sold"
  },
  {
    "id": 8561,
    "category": {
      "id": 1366825701,
      "name": "automation"
    },
    "name": "hello kity",
    "photoUrls": [
      "foo.bar.com/1",
      "foo.bar.com/2"
    ],
    "tags": [
      {
        "id": 332,
        "name": "tagss"
      }
    ],
    "status": "sold"
  },
  {
    "id": 9560,
    "category": {
      "id": 1366825701,
      "name": "automation"
    },
    "name": "hello kity",
    "photoUrls": [
      "foo.bar.com/1",
      "foo.bar.com/2"
    ],
    "tags": [
      {
        "id": 332,
        "name": "tagss"
      }
    ],
    "status": "sold"
  },
  {
    "id": 4558,
    "category": {
      "id": 1366825701,
      "name": "automation"
    },
    "name": "hello kity",
    "photoUrls": [
      "foo.bar.com/1",
      "foo.bar.com/2"
    ],
    "tags": [
      {
        "id": 332,
        "name": "tagss"
      }
    ],
    "status": "sold"
  },
  {
    "id": 1234,
    "category": {
      "id": 0,
      "name": "string"
    },
    "name": "doggie2",
    "photoUrls": [
      "string"
    ],
    "tags": [
      {
        "id": 0,
        "name": "string"
      }
    ],
    "status": "sold"
  },
  {
    "id": 20593238,
    "category": {
      "id": 96650357,
      "name": "ut aute"
    },
    "name": "doggie",
    "photoUrls": [
      "in deserunt sit qui elit",
      "do dolore"
    ],
    "tags": [
      {
        "id": 80489283,
        "name": "dolore elit aute Excepteur anim"
      },
      {
        "id": -29854588,
        "name": "enim"
      }
    ],
    "status": "sold"
  },
  {
    "id": 19930,
    "category": {
      "id": 0,
      "name": "string"
    },
    "name": "name changed pet",
    "photoUrls": [
      "string"
    ],
    "tags": [
      {
        "id": 0,
        "name": "nice"
      }
    ],
    "status": "sold"
  },
  {
    "id": 19931,
    "category": {
      "id": 0,
      "name": "string"
    },
    "name": "test changed",
    "photoUrls": [
      "string"
    ],
    "tags": [
      {
        "id": 0,
        "name": "string"
      }
    ],
    "status": "sold"
  },
  {
    "id": 9223372036854776000,
    "category": {
      "id": 0,
      "name": "cats"
    },
    "name": "catswomen",
    "photoUrls": [
      "string"
    ],
    "tags": [
      {
        "id": 0,
        "name": "strits"
      }
    ],
    "status": "sold"
  },
  {
    "id": 9223372036854776000,
    "category": {
      "id": 0,
      "name": "cats"
    },
    "name": "catswomen",
    "photoUrls": [
      "string"
    ],
    "tags": [
      {
        "id": 0,
        "name": "strits"
      }
    ],
    "status": "sold"
  },
  {
    "id": 5396,
    "category": {
      "id": 2990,
      "name": "Labrador"
    },
    "name": "Molly",
    "photoUrls": [
      "nemo_necessitatibus/repellendus.gif"
    ],
    "tags": [
      {
        "id": 0,
        "name": "Molly"
      }
    ],
    "status": "sold"
  },
  {
    "id": 1601,
    "category": {
      "id": 1,
      "name": "Dogs"
    },
    "name": "Akira The Shiba Inu",
    "photoUrls": [
      "string"
    ],
    "tags": [
      {
        "id": 0,
        "name": "string"
      }
    ],
    "status": "sold"
  },
  {
    "id": 7574746,
    "category": {
      "id": 1,
      "name": "Cat"
    },
    "name": "Hardy",
    "photoUrls": [
      "https://i.pinimg.com/originals/5c/2c/44/5c2c44f16da1caf134c00bc4f9c72ea0.jpg"
    ],
    "tags": [
      {
        "id": 7805,
        "name": "Mainecoon"
      }
    ],
    "status": "sold"
  },
  {
    "id": 3,
    "category": {
      "id": 0,
      "name": "string"
    },
    "name": "doggie 3 name changed",
    "photoUrls": [
      "string"
    ],
    "tags": [
      {
        "id": 0,
        "name": "string"
      }
    ],
    "status": "sold"
  },
  {
    "id": 568696896899689660,
    "category": {
      "id": 786587678,
      "name": "string"
    },
    "name": "DogNaMeh",
    "photoUrls": [
      "string"
    ],
    "tags": [
      {
        "id": 7547646785,
        "name": "string"
      }
    ],
    "status": "sold"
  },
  {
    "id": 5686968968996897000,
    "category": {
      "id": 786587678,
      "name": "string"
    },
    "name": "DogNaMeh",
    "photoUrls": [
      "string"
    ],
    "tags": [
      {
        "id": 7547646785,
        "name": "string"
      }
    ],
    "status": "sold"
  },
  {
    "id": 488,
    "category": {
      "id": 1366825701,
      "name": "automation"
    },
    "name": "hello kity",
    "photoUrls": [
      "foo.bar.com/1",
      "foo.bar.com/2"
    ],
    "tags": [
      {
        "id": 332,
        "name": "tagss"
      }
    ],
    "status": "sold"
  },
  {
    "id": 56331470,
    "category": {
      "id": 28262311,
      "name": "nostrud proident"
    },
    "name": "doggie",
    "photoUrls": [
      "sunt dolor veniam aliqua",
      "nulla anim ex"
    ],
    "tags": [
      {
        "id": 21515670,
        "name": "voluptate in elit ani"
      },
      {
        "id": -36858804,
        "name": "proident non deserunt"
      }
    ],
    "status": "sold"
  },
  {
    "id": 2680,
    "category": {
      "id": 1366825701,
      "name": "automation"
    },
    "name": "hello kity",
    "photoUrls": [
      "foo.bar.com/1",
      "foo.bar.com/2"
    ],
    "tags": [
      {
        "id": 332,
        "name": "tagss"
      }
    ],
    "status": "sold"
  },
  {
    "id": 9810,
    "category": {
      "id": 1366825701,
      "name": "automation"
    },
    "name": "hello kity",
    "photoUrls": [
      "foo.bar.com/1",
      "foo.bar.com/2"
    ],
    "tags": [
      {
        "id": 332,
        "name": "tagss"
      }
    ],
    "status": "sold"
  },
  {
    "id": 2256,
    "category": {
      "id": 1366825701,
      "name": "automation"
    },
    "name": "hello kity",
    "photoUrls": [
      "foo.bar.com/1",
      "foo.bar.com/2"
    ],
    "tags": [
      {
        "id": 332,
        "name": "tagss"
      }
    ],
    "status": "sold"
  },
  {
    "id": 5600,
    "category": {
      "id": 1366825701,
      "name": "automation"
    },
    "name": "hello kity",
    "photoUrls": [
      "foo.bar.com/1",
      "foo.bar.com/2"
    ],
    "tags": [
      {
        "id": 332,
        "name": "tagss"
      }
    ],
    "status": "sold"
  },
  {
    "id": 9223372036854775000,
    "category": {
      "id": 0,
      "name": "string"
    },
    "name": "fish",
    "photoUrls": [
      "string"
    ],
    "tags": [
      {
        "id": 0,
        "name": "string"
      }
    ],
    "status": "sold"
  },
  {
    "id": 3227,
    "category": {
      "id": 1366825701,
      "name": "automation"
    },
    "name": "hello kity",
    "photoUrls": [
      "foo.bar.com/1",
      "foo.bar.com/2"
    ],
    "tags": [
      {
        "id": 332,
        "name": "tagss"
      }
    ],
    "status": "sold"
  },
  {
    "id": 6242,
    "category": {
      "id": 1366825701,
      "name": "automation"
    },
    "name": "hello kity",
    "photoUrls": [
      "foo.bar.com/1",
      "foo.bar.com/2"
    ],
    "tags": [
      {
        "id": 332,
        "name": "tagss"
      }
    ],
    "status": "sold"
  },
  {
    "id": 4715,
    "category": {
      "id": 1366825701,
      "name": "automation"
    },
    "name": "hello kity",
    "photoUrls": [
      "foo.bar.com/1",
      "foo.bar.com/2"
    ],
    "tags": [
      {
        "id": 332,
        "name": "tagss"
      }
    ],
    "status": "sold"
  },
  {
    "id": 3903023,
    "category": {
      "id": -56789506,
      "name": "cillum p"
    },
    "name": "doggie",
    "photoUrls": [
      "aliquip Excepteur",
      "commodo dolore consequat eu"
    ],
    "tags": [
      {
        "id": 60937326,
        "name": "irure in"
      },
      {
        "id": 20218536,
        "name": "sint consectetur ad voluptate"
      }
    ],
    "status": "sold"
  },
  {
    "id": 3708840,
    "category": {
      "id": 9855812,
      "name": "Duis in commodo"
    },
    "name": "doggie",
    "photoUrls": [
      "minim id in sit",
      "est esse culpa nisi"
    ],
    "tags": [
      {
        "id": -89808508,
        "name": "sit"
      },
      {
        "id": -5238278,
        "name": "dolor in"
      }
    ],
    "status": "sold"
  },
  {
    "id": 24093935,
    "category": {
      "id": -6714225,
      "name": "do magna"
    },
    "name": "doggie",
    "photoUrls": [
      "aute",
      "velit"
    ],
    "tags": [
      {
        "id": 71561130,
        "name": "deserunt ut occaecat"
      },
      {
        "id": -1195842,
        "name": "nulla nostrud occaeca"
      }
    ],
    "status": "sold"
  },
  {
    "id": 91507602,
    "category": {
      "id": -95494262,
      "name": "sit ea"
    },
    "name": "doggie",
    "photoUrls": [
      "deserunt",
      "id sint et"
    ],
    "tags": [
      {
        "id": -54029842,
        "name": "ullamco"
      },
      {
        "id": 13198949,
        "name": "id"
      }
    ],
    "status": "sold"
  },
  {
    "id": 832,
    "category": {
      "id": 1366825701,
      "name": "automation"
    },
    "name": "hello kity",
    "photoUrls": [
      "foo.bar.com/1",
      "foo.bar.com/2"
    ],
    "tags": [
      {
        "id": 332,
        "name": "tagss"
      }
    ],
    "status": "sold"
  },
  {
    "id": 5230,
    "category": {
      "id": 1366825701,
      "name": "automation"
    },
    "name": "hello kity",
    "photoUrls": [
      "foo.bar.com/1",
      "foo.bar.com/2"
    ],
    "tags": [
      {
        "id": 332,
        "name": "tagss"
      }
    ],
    "status": "sold"
  },
  {
    "id": 2145,
    "category": {
      "id": 1366825701,
      "name": "automation"
    },
    "name": "hello kity",
    "photoUrls": [
      "foo.bar.com/1",
      "foo.bar.com/2"
    ],
    "tags": [
      {
        "id": 332,
        "name": "tagss"
      }
    ],
    "status": "sold"
  },
  {
    "id": 13,
    "category": {
      "id": 0,
      "name": "cats"
    },
    "photoUrls": [
      "string"
    ],
    "tags": [
      {
        "id": 0,
        "name": "string"
      }
    ],
    "status": "sold"
  },
  {
    "id": 165,
    "category": {
      "id": 161,
      "name": "test"
    },
    "name": "Muffy",
    "photoUrls": [
      "string"
    ],
    "tags": [
      {
        "id": 0,
        "name": "string"
      }
    ],
    "status": "sold"
  },
  {
    "id": 8819,
    "category": {
      "id": 1366825701,
      "name": "automation"
    },
    "name": "hello kity",
    "photoUrls": [
      "foo.bar.com/1",
      "foo.bar.com/2"
    ],
    "tags": [
      {
        "id": 332,
        "name": "tagss"
      }
    ],
    "status": "sold"
  },
  {
    "id": 5348,
    "category": {
      "id": 1366825701,
      "name": "automation"
    },
    "name": "hello kity",
    "photoUrls": [
      "foo.bar.com/1",
      "foo.bar.com/2"
    ],
    "tags": [
      {
        "id": 332,
        "name": "tagss"
      }
    ],
    "status": "sold"
  }
]